README.md
setup.py
keras_rnadam/__init__.py
keras_rnadam/backend.py
keras_rnadam/optimizers.py
keras_rnadam.egg-info/PKG-INFO
keras_rnadam.egg-info/SOURCES.txt
keras_rnadam.egg-info/dependency_links.txt
keras_rnadam.egg-info/requirements.txt
keras_rnadam.egg-info/requires.txt
keras_rnadam.egg-info/top_level.txt