Metadata-Version: 2.1
Name: keras-rnadam
Version: 0.2.0
Summary: Rectified Nadam implemented in Keras
Home-page: https://github.com/niley1nov/keras_rnadam/archive/0.2.0.tar.gz
Author: niley1nov
Author-email: nilaysharma1nov@gmail.com
License: MIT
Platform: UNKNOWN
Classifier: Programming Language :: Python :: 3.7
Classifier: License :: OSI Approved :: MIT License
Classifier: Operating System :: OS Independent
